[
  {
    "title": "Hate Love Songs",
    "artist": "Gwar",
    "album": "Carnival of Chaos"
  },
  {
    "title": "If I Could Be That",
    "artist": "Gwar",
    "album": "Carnival of Chaos"
  },
  {
    "title": "Razones",
    "artist": "Discordia",
    "album": "Todo Empieza Hoy"
  },
  {
    "title": "I Suck on My Thumb",
    "artist": "Gwar",
    "album": "Carnival of Chaos"
  },
  {
    "title": "Sexecutioner",
    "artist": "Gwar",
    "album": "Scumdogs of the Universe"
  },
  {
    "title": "Me corten la lengua",
    "artist": "Marea",
    "album": "Las aceras estan llenas de piojos"
  }
]