[
  {
    "title": "Spotlight",
    "artist": "Jennifer Hudson",
    "album": "Jennifer Hudson"
  },
  {
    "title": "I Wanna Dance with Somebody (Who Loves Me)",
    "artist": "Whitney Houston",
    "album": "Whitney"
  },
  {
    "title": "Toxic",
    "artist": "Britney Spears",
    "album": "In The Zone"
  },
  {
    "title": "Survivor",
    "artist": "Destiny's Child",
    "album": "Survivor"
  },
  {
    "title": "Jumpin', Jumpin'",
    "artist": "Destiny's Child",
    "album": "The Writing's On The Wall"
  },
  {
    "title": "Say My Name",
    "artist": "Destiny's Child",
    "album": "The Writing's On The Wall"
  }
]