[
  {
    "title": "Slow Slow Tune",
    "artist": "My Morning Jacket",
    "album": "Circuital"
  },
  {
    "title": "It Beats For You",
    "artist": "My Morning Jacket",
    "album": "Z"
  },
  {
    "title": "Rocket Man",
    "artist": "My Morning Jacket",
    "album": "Chapter 1: The Sandworm Cometh - Early Recordings, B-Sides, Covers, y Mas"
  },
  {
    "title": "Touch Me I'm Going To Scream, Pt. 1",
    "artist": "My Morning Jacket",
    "album": "Evil Urges"
  },
  {
    "title": "Dondante",
    "artist": "My Morning Jacket",
    "album": "Z"
  },
  {
    "title": "I'm Amazed",
    "artist": "My Morning Jacket",
    "album": "Evil Urges"
  }
]